<annotation><filename>for_xml_1889.jpg</filename><object><name>6</name><bndbox><xmin>60</xmin><ymin>62</ymin><xmax>108</xmax><ymax>145</ymax></bndbox></object><object><name>3</name><bndbox><xmin>96</xmin><ymin>54</ymin><xmax>141</xmax><ymax>142</ymax></bndbox></object><object><name>پ</name><bndbox><xmin>134</xmin><ymin>57</ymin><xmax>200</xmax><ymax>153</ymax></bndbox></object><object><name>1</name><bndbox><xmin>190</xmin><ymin>46</ymin><xmax>234</xmax><ymax>144</ymax></bndbox></object><object><name>5</name><bndbox><xmin>226</xmin><ymin>41</ymin><xmax>264</xmax><ymax>133</ymax></bndbox></object><object><name>2</name><bndbox><xmin>254</xmin><ymin>40</ymin><xmax>296</xmax><ymax>125</ymax></bndbox></object><object><name>1</name><bndbox><xmin>294</xmin><ymin>49</ymin><xmax>333</xmax><ymax>126</ymax></bndbox></object><object><name>1</name><bndbox><xmin>320</xmin><ymin>44</ymin><xmax>372</xmax><ymax>124</ymax></bndbox></object><folder /></annotation>