<annotation><filename>for_xml_121026.jpg</filename><object><name>1</name><bndbox><xmin>66</xmin><ymin>17</ymin><xmax>102</xmax><ymax>115</ymax></bndbox></object><object><name>1</name><bndbox><xmin>107</xmin><ymin>22</ymin><xmax>142</xmax><ymax>122</ymax></bndbox></object><object><name>ت</name><bndbox><xmin>147</xmin><ymin>71</ymin><xmax>228</xmax><ymax>131</ymax></bndbox></object><object><name>2</name><bndbox><xmin>237</xmin><ymin>44</ymin><xmax>284</xmax><ymax>143</ymax></bndbox></object><object><name>4</name><bndbox><xmin>287</xmin><ymin>54</ymin><xmax>331</xmax><ymax>147</ymax></bndbox></object><object><name>3</name><bndbox><xmin>336</xmin><ymin>61</ymin><xmax>384</xmax><ymax>155</ymax></bndbox></object><object><name>1</name><bndbox><xmin>404</xmin><ymin>89</ymin><xmax>437</xmax><ymax>172</ymax></bndbox></object><object><name>9</name><bndbox><xmin>446</xmin><ymin>97</ymin><xmax>489</xmax><ymax>180</ymax></bndbox></object><folder /></annotation>