<annotation><filename>for_xml_122322.jpg</filename><object><name>4</name><bndbox><xmin>27</xmin><ymin>5</ymin><xmax>47</xmax><ymax>42</ymax></bndbox></object><object><name>9</name><bndbox><xmin>47</xmin><ymin>7</ymin><xmax>68</xmax><ymax>44</ymax></bndbox></object><object><name>ت</name><bndbox><xmin>70</xmin><ymin>21</ymin><xmax>105</xmax><ymax>43</ymax></bndbox></object><object><name>2</name><bndbox><xmin>106</xmin><ymin>7</ymin><xmax>127</xmax><ymax>44</ymax></bndbox></object><object><name>8</name><bndbox><xmin>126</xmin><ymin>9</ymin><xmax>146</xmax><ymax>45</ymax></bndbox></object><object><name>6</name><bndbox><xmin>145</xmin><ymin>8</ymin><xmax>166</xmax><ymax>45</ymax></bndbox></object><object><name>2</name><bndbox><xmin>171</xmin><ymin>14</ymin><xmax>190</xmax><ymax>47</ymax></bndbox></object><object><name>2</name><bndbox><xmin>190</xmin><ymin>14</ymin><xmax>209</xmax><ymax>47</ymax></bndbox></object><folder /></annotation>