<annotation><filename>for_xml_126580.jpg</filename><object><name>1</name><bndbox><xmin>61</xmin><ymin>129</ymin><xmax>111</xmax><ymax>203</ymax></bndbox></object><object><name>9</name><bndbox><xmin>101</xmin><ymin>116</ymin><xmax>158</xmax><ymax>187</ymax></bndbox></object><object><name>ت</name><bndbox><xmin>158</xmin><ymin>117</ymin><xmax>227</xmax><ymax>175</ymax></bndbox></object><object><name>3</name><bndbox><xmin>215</xmin><ymin>67</ymin><xmax>263</xmax><ymax>150</ymax></bndbox></object><object><name>8</name><bndbox><xmin>261</xmin><ymin>55</ymin><xmax>309</xmax><ymax>137</ymax></bndbox></object><object><name>7</name><bndbox><xmin>292</xmin><ymin>39</ymin><xmax>340</xmax><ymax>122</ymax></bndbox></object><object><name>3</name><bndbox><xmin>342</xmin><ymin>35</ymin><xmax>384</xmax><ymax>112</ymax></bndbox></object><object><name>3</name><bndbox><xmin>380</xmin><ymin>21</ymin><xmax>423</xmax><ymax>96</ymax></bndbox></object><folder /></annotation>