<annotation><filename>for_xml_132288.jpg</filename><object><name>1</name><bndbox><xmin>34</xmin><ymin>73</ymin><xmax>59</xmax><ymax>145</ymax></bndbox></object><object><name>7</name><bndbox><xmin>54</xmin><ymin>65</ymin><xmax>84</xmax><ymax>140</ymax></bndbox></object><object><name>ت</name><bndbox><xmin>82</xmin><ymin>78</ymin><xmax>126</xmax><ymax>127</ymax></bndbox></object><object><name>6</name><bndbox><xmin>123</xmin><ymin>40</ymin><xmax>154</xmax><ymax>118</ymax></bndbox></object><object><name>5</name><bndbox><xmin>148</xmin><ymin>34</ymin><xmax>179</xmax><ymax>110</ymax></bndbox></object><object><name>7</name><bndbox><xmin>175</xmin><ymin>23</ymin><xmax>207</xmax><ymax>100</ymax></bndbox></object><object><name>1</name><bndbox><xmin>205</xmin><ymin>23</ymin><xmax>233</xmax><ymax>96</ymax></bndbox></object><object><name>1</name><bndbox><xmin>231</xmin><ymin>16</ymin><xmax>262</xmax><ymax>94</ymax></bndbox></object><folder /></annotation>