<annotation><filename>for_xml_134299.jpg</filename><object><name>1</name><bndbox><xmin>15</xmin><ymin>5</ymin><xmax>27</xmax><ymax>31</ymax></bndbox></object><object><name>4</name><bndbox><xmin>26</xmin><ymin>7</ymin><xmax>38</xmax><ymax>32</ymax></bndbox></object><object><name>ت</name><bndbox><xmin>37</xmin><ymin>16</ymin><xmax>59</xmax><ymax>33</ymax></bndbox></object><object><name>6</name><bndbox><xmin>59</xmin><ymin>10</ymin><xmax>72</xmax><ymax>33</ymax></bndbox></object><object><name>5</name><bndbox><xmin>71</xmin><ymin>11</ymin><xmax>83</xmax><ymax>34</ymax></bndbox></object><object><name>8</name><bndbox><xmin>82</xmin><ymin>12</ymin><xmax>95</xmax><ymax>35</ymax></bndbox></object><object><name>3</name><bndbox><xmin>97</xmin><ymin>17</ymin><xmax>109</xmax><ymax>38</ymax></bndbox></object><object><name>3</name><bndbox><xmin>109</xmin><ymin>18</ymin><xmax>120</xmax><ymax>39</ymax></bndbox></object><folder /></annotation>