<annotation><filename>for_xml_132962.jpg</filename><object><name>8</name><bndbox><xmin>16</xmin><ymin>46</ymin><xmax>32</xmax><ymax>79</ymax></bndbox></object><object><name>6</name><bndbox><xmin>31</xmin><ymin>40</ymin><xmax>46</xmax><ymax>77</ymax></bndbox></object><object><name>ی</name><bndbox><xmin>48</xmin><ymin>33</ymin><xmax>72</xmax><ymax>68</ymax></bndbox></object><object><name>4</name><bndbox><xmin>73</xmin><ymin>27</ymin><xmax>88</xmax><ymax>63</ymax></bndbox></object><object><name>3</name><bndbox><xmin>88</xmin><ymin>21</ymin><xmax>103</xmax><ymax>58</ymax></bndbox></object><object><name>8</name><bndbox><xmin>101</xmin><ymin>18</ymin><xmax>116</xmax><ymax>54</ymax></bndbox></object><object><name>9</name><bndbox><xmin>118</xmin><ymin>19</ymin><xmax>133</xmax><ymax>49</ymax></bndbox></object><object><name>9</name><bndbox><xmin>131</xmin><ymin>15</ymin><xmax>146</xmax><ymax>46</ymax></bndbox></object><folder /></annotation>