<annotation><filename>for_xml_124192.jpg</filename><object><name>5</name><bndbox><xmin>26</xmin><ymin>11</ymin><xmax>53</xmax><ymax>53</ymax></bndbox></object><object><name>7</name><bndbox><xmin>54</xmin><ymin>14</ymin><xmax>79</xmax><ymax>57</ymax></bndbox></object><object><name>ه‍</name><bndbox><xmin>80</xmin><ymin>24</ymin><xmax>119</xmax><ymax>64</ymax></bndbox></object><object><name>9</name><bndbox><xmin>124</xmin><ymin>29</ymin><xmax>149</xmax><ymax>72</ymax></bndbox></object><object><name>3</name><bndbox><xmin>150</xmin><ymin>35</ymin><xmax>177</xmax><ymax>76</ymax></bndbox></object><object><name>1</name><bndbox><xmin>179</xmin><ymin>41</ymin><xmax>195</xmax><ymax>83</ymax></bndbox></object><object><name>6</name><bndbox><xmin>201</xmin><ymin>55</ymin><xmax>228</xmax><ymax>90</ymax></bndbox></object><object><name>6</name><bndbox><xmin>227</xmin><ymin>59</ymin><xmax>254</xmax><ymax>95</ymax></bndbox></object><folder /></annotation>