<annotation><filename>for_xml_787.jpg</filename><object><name>6</name><bndbox><xmin>79</xmin><ymin>72</ymin><xmax>153</xmax><ymax>193</ymax></bndbox></object><object><name>1</name><bndbox><xmin>139</xmin><ymin>72</ymin><xmax>195</xmax><ymax>191</ymax></bndbox></object><object><name>ه‍</name><bndbox><xmin>186</xmin><ymin>84</ymin><xmax>270</xmax><ymax>191</ymax></bndbox></object><object><name>9</name><bndbox><xmin>253</xmin><ymin>70</ymin><xmax>318</xmax><ymax>202</ymax></bndbox></object><object><name>7</name><bndbox><xmin>302</xmin><ymin>60</ymin><xmax>360</xmax><ymax>200</ymax></bndbox></object><object><name>5</name><bndbox><xmin>344</xmin><ymin>70</ymin><xmax>407</xmax><ymax>181</ymax></bndbox></object><object><name>1</name><bndbox><xmin>402</xmin><ymin>65</ymin><xmax>460</xmax><ymax>191</ymax></bndbox></object><object><name>0</name><bndbox><xmin>446</xmin><ymin>91</ymin><xmax>500</xmax><ymax>179</ymax></bndbox></object><folder /></annotation>