<annotation><filename>for_xml_857.jpg</filename><object><name>4</name><bndbox><xmin>72</xmin><ymin>38</ymin><xmax>117</xmax><ymax>129</ymax></bndbox></object><object><name>7</name><bndbox><xmin>109</xmin><ymin>37</ymin><xmax>154</xmax><ymax>129</ymax></bndbox></object><object><name>ه‍</name><bndbox><xmin>147</xmin><ymin>59</ymin><xmax>212</xmax><ymax>140</ymax></bndbox></object><object><name>6</name><bndbox><xmin>210</xmin><ymin>36</ymin><xmax>250</xmax><ymax>150</ymax></bndbox></object><object><name>8</name><bndbox><xmin>242</xmin><ymin>47</ymin><xmax>287</xmax><ymax>135</ymax></bndbox></object><object><name>4</name><bndbox><xmin>283</xmin><ymin>41</ymin><xmax>325</xmax><ymax>134</ymax></bndbox></object><object><name>7</name><bndbox><xmin>322</xmin><ymin>58</ymin><xmax>370</xmax><ymax>126</ymax></bndbox></object><object><name>7</name><bndbox><xmin>364</xmin><ymin>46</ymin><xmax>409</xmax><ymax>137</ymax></bndbox></object><folder /></annotation>