<annotation><filename>for_xml_137992.jpg</filename><object><name>6</name><bndbox><xmin>69</xmin><ymin>63</ymin><xmax>121</xmax><ymax>175</ymax></bndbox></object><object><name>1</name><bndbox><xmin>116</xmin><ymin>65</ymin><xmax>170</xmax><ymax>178</ymax></bndbox></object><object><name>ن</name><bndbox><xmin>177</xmin><ymin>73</ymin><xmax>248</xmax><ymax>191</ymax></bndbox></object><object><name>4</name><bndbox><xmin>251</xmin><ymin>70</ymin><xmax>303</xmax><ymax>200</ymax></bndbox></object><object><name>5</name><bndbox><xmin>298</xmin><ymin>75</ymin><xmax>355</xmax><ymax>198</ymax></bndbox></object><object><name>9</name><bndbox><xmin>347</xmin><ymin>81</ymin><xmax>410</xmax><ymax>203</ymax></bndbox></object><object><name>8</name><bndbox><xmin>409</xmin><ymin>99</ymin><xmax>467</xmax><ymax>207</ymax></bndbox></object><folder /></annotation>