<annotation><filename>for_xml_6084.jpg</filename><object><name>3</name><bndbox><xmin>113</xmin><ymin>34</ymin><xmax>207</xmax><ymax>193</ymax></bndbox></object><object><name>3</name><bndbox><xmin>206</xmin><ymin>38</ymin><xmax>313</xmax><ymax>200</ymax></bndbox></object><object><name>ل</name><bndbox><xmin>336</xmin><ymin>50</ymin><xmax>470</xmax><ymax>207</ymax></bndbox></object><object><name>9</name><bndbox><xmin>488</xmin><ymin>57</ymin><xmax>597</xmax><ymax>215</ymax></bndbox></object><object><name>9</name><bndbox><xmin>589</xmin><ymin>57</ymin><xmax>688</xmax><ymax>229</ymax></bndbox></object><object><name>8</name><bndbox><xmin>689</xmin><ymin>74</ymin><xmax>788</xmax><ymax>225</ymax></bndbox></object><object><name>4</name><bndbox><xmin>814</xmin><ymin>113</ymin><xmax>909</xmax><ymax>238</ymax></bndbox></object><object><name>1</name><bndbox><xmin>922</xmin><ymin>111</ymin><xmax>1002</xmax><ymax>247</ymax></bndbox></object><folder /></annotation>