<annotation><filename>for_xml_130437.jpg</filename><object><name>2</name><bndbox><xmin>79</xmin><ymin>28</ymin><xmax>145</xmax><ymax>135</ymax></bndbox></object><object><name>5</name><bndbox><xmin>142</xmin><ymin>39</ymin><xmax>211</xmax><ymax>145</ymax></bndbox></object><object><name>пи</name><bndbox><xmin>222</xmin><ymin>51</ymin><xmax>319</xmax><ymax>160</ymax></bndbox></object><object><name>6</name><bndbox><xmin>332</xmin><ymin>65</ymin><xmax>412</xmax><ymax>170</ymax></bndbox></object><object><name>8</name><bndbox><xmin>408</xmin><ymin>76</ymin><xmax>478</xmax><ymax>184</ymax></bndbox></object><object><name>7</name><bndbox><xmin>482</xmin><ymin>81</ymin><xmax>558</xmax><ymax>190</ymax></bndbox></object><object><name>1</name><bndbox><xmin>578</xmin><ymin>114</ymin><xmax>631</xmax><ymax>205</ymax></bndbox></object><object><name>0</name><bndbox><xmin>644</xmin><ymin>140</ymin><xmax>697</xmax><ymax>198</ymax></bndbox></object><folder /></annotation>