<annotation><filename>for_xml_1464.jpg</filename><object><name>7</name><bndbox><xmin>85</xmin><ymin>117</ymin><xmax>145</xmax><ymax>261</ymax></bndbox></object><object><name>7</name><bndbox><xmin>141</xmin><ymin>103</ymin><xmax>203</xmax><ymax>241</ymax></bndbox></object><object><name>ุณ</name><bndbox><xmin>208</xmin><ymin>100</ymin><xmax>306</xmax><ymax>215</ymax></bndbox></object><object><name>8</name><bndbox><xmin>315</xmin><ymin>69</ymin><xmax>369</xmax><ymax>187</ymax></bndbox></object><object><name>4</name><bndbox><xmin>362</xmin><ymin>55</ymin><xmax>408</xmax><ymax>183</ymax></bndbox></object><object><name>8</name><bndbox><xmin>418</xmin><ymin>40</ymin><xmax>472</xmax><ymax>164</ymax></bndbox></object><object><name>8</name><bndbox><xmin>479</xmin><ymin>58</ymin><xmax>524</xmax><ymax>156</ymax></bndbox></object><object><name>8</name><bndbox><xmin>516</xmin><ymin>46</ymin><xmax>572</xmax><ymax>151</ymax></bndbox></object><folder /></annotation>