<annotation><filename>for_xml_4749.jpg</filename><object><name>2</name><bndbox><xmin>58</xmin><ymin>67</ymin><xmax>103</xmax><ymax>159</ymax></bndbox></object><object><name>8</name><bndbox><xmin>106</xmin><ymin>64</ymin><xmax>150</xmax><ymax>156</ymax></bndbox></object><object><name>ุณ</name><bndbox><xmin>149</xmin><ymin>59</ymin><xmax>227</xmax><ymax>152</ymax></bndbox></object><object><name>2</name><bndbox><xmin>234</xmin><ymin>46</ymin><xmax>277</xmax><ymax>135</ymax></bndbox></object><object><name>2</name><bndbox><xmin>281</xmin><ymin>41</ymin><xmax>320</xmax><ymax>135</ymax></bndbox></object><object><name>1</name><bndbox><xmin>331</xmin><ymin>39</ymin><xmax>365</xmax><ymax>123</ymax></bndbox></object><object><name>9</name><bndbox><xmin>373</xmin><ymin>33</ymin><xmax>413</xmax><ymax>127</ymax></bndbox></object><object><name>9</name><bndbox><xmin>416</xmin><ymin>37</ymin><xmax>457</xmax><ymax>123</ymax></bndbox></object><folder /></annotation>