<annotation><filename>for_xml_125787.jpg</filename><object><name>6</name><bndbox><xmin>9</xmin><ymin>7</ymin><xmax>20</xmax><ymax>26</ymax></bndbox></object><object><name>8</name><bndbox><xmin>19</xmin><ymin>6</ymin><xmax>30</xmax><ymax>24</ymax></bndbox></object><object><name>و</name><bndbox><xmin>32</xmin><ymin>6</ymin><xmax>43</xmax><ymax>23</ymax></bndbox></object><object><name>5</name><bndbox><xmin>45</xmin><ymin>5</ymin><xmax>56</xmax><ymax>23</ymax></bndbox></object><object><name>2</name><bndbox><xmin>55</xmin><ymin>4</ymin><xmax>64</xmax><ymax>22</ymax></bndbox></object><object><name>4</name><bndbox><xmin>63</xmin><ymin>4</ymin><xmax>72</xmax><ymax>22</ymax></bndbox></object><object><name>1</name><bndbox><xmin>74</xmin><ymin>6</ymin><xmax>82</xmax><ymax>23</ymax></bndbox></object><object><name>1</name><bndbox><xmin>81</xmin><ymin>5</ymin><xmax>89</xmax><ymax>22</ymax></bndbox></object><folder /></annotation>