<annotation><filename>for_xml_133780.jpg</filename><object><name>6</name><bndbox><xmin>60</xmin><ymin>20</ymin><xmax>103</xmax><ymax>112</ymax></bndbox></object><object><name>8</name><bndbox><xmin>106</xmin><ymin>18</ymin><xmax>153</xmax><ymax>112</ymax></bndbox></object><object><name>و</name><bndbox><xmin>165</xmin><ymin>25</ymin><xmax>213</xmax><ymax>114</ymax></bndbox></object><object><name>7</name><bndbox><xmin>227</xmin><ymin>23</ymin><xmax>276</xmax><ymax>122</ymax></bndbox></object><object><name>2</name><bndbox><xmin>276</xmin><ymin>24</ymin><xmax>320</xmax><ymax>127</ymax></bndbox></object><object><name>7</name><bndbox><xmin>320</xmin><ymin>25</ymin><xmax>370</xmax><ymax>128</ymax></bndbox></object><object><name>2</name><bndbox><xmin>380</xmin><ymin>46</ymin><xmax>429</xmax><ymax>134</ymax></bndbox></object><object><name>4</name><bndbox><xmin>428</xmin><ymin>44</ymin><xmax>474</xmax><ymax>136</ymax></bndbox></object><folder /></annotation>