<annotation><filename>for_xml_136202.jpg</filename><object><name>5</name><bndbox><xmin>98</xmin><ymin>34</ymin><xmax>184</xmax><ymax>171</ymax></bndbox></object><object><name>6</name><bndbox><xmin>182</xmin><ymin>33</ymin><xmax>271</xmax><ymax>168</ymax></bndbox></object><object><name>و</name><bndbox><xmin>298</xmin><ymin>41</ymin><xmax>399</xmax><ymax>163</ymax></bndbox></object><object><name>9</name><bndbox><xmin>428</xmin><ymin>40</ymin><xmax>513</xmax><ymax>173</ymax></bndbox></object><object><name>5</name><bndbox><xmin>513</xmin><ymin>41</ymin><xmax>598</xmax><ymax>176</ymax></bndbox></object><object><name>3</name><bndbox><xmin>603</xmin><ymin>38</ymin><xmax>688</xmax><ymax>177</ymax></bndbox></object><object><name>2</name><bndbox><xmin>707</xmin><ymin>67</ymin><xmax>788</xmax><ymax>181</ymax></bndbox></object><object><name>4</name><bndbox><xmin>787</xmin><ymin>69</ymin><xmax>864</xmax><ymax>185</ymax></bndbox></object><folder /></annotation>