<annotation><filename>for_xml_120666.jpg</filename><object><name>4</name><bndbox><xmin>35</xmin><ymin>5</ymin><xmax>63</xmax><ymax>57</ymax></bndbox></object><object><name>2</name><bndbox><xmin>63</xmin><ymin>5</ymin><xmax>93</xmax><ymax>58</ymax></bndbox></object><object><name>ج</name><bndbox><xmin>96</xmin><ymin>4</ymin><xmax>139</xmax><ymax>62</ymax></bndbox></object><object><name>8</name><bndbox><xmin>144</xmin><ymin>8</ymin><xmax>175</xmax><ymax>61</ymax></bndbox></object><object><name>9</name><bndbox><xmin>174</xmin><ymin>9</ymin><xmax>203</xmax><ymax>62</ymax></bndbox></object><object><name>2</name><bndbox><xmin>202</xmin><ymin>9</ymin><xmax>231</xmax><ymax>62</ymax></bndbox></object><object><name>2</name><bndbox><xmin>238</xmin><ymin>20</ymin><xmax>265</xmax><ymax>65</ymax></bndbox></object><object><name>2</name><bndbox><xmin>267</xmin><ymin>19</ymin><xmax>294</xmax><ymax>66</ymax></bndbox></object><folder /></annotation>