<annotation><filename>for_xml_124189.jpg</filename><object><name>1</name><bndbox><xmin>33</xmin><ymin>107</ymin><xmax>62</xmax><ymax>185</ymax></bndbox></object><object><name>3</name><bndbox><xmin>61</xmin><ymin>92</ymin><xmax>98</xmax><ymax>176</ymax></bndbox></object><object><name>ج</name><bndbox><xmin>100</xmin><ymin>74</ymin><xmax>147</xmax><ymax>160</ymax></bndbox></object><object><name>2</name><bndbox><xmin>147</xmin><ymin>56</ymin><xmax>184</xmax><ymax>146</ymax></bndbox></object><object><name>8</name><bndbox><xmin>179</xmin><ymin>45</ymin><xmax>213</xmax><ymax>131</ymax></bndbox></object><object><name>9</name><bndbox><xmin>208</xmin><ymin>36</ymin><xmax>245</xmax><ymax>118</ymax></bndbox></object><object><name>5</name><bndbox><xmin>243</xmin><ymin>32</ymin><xmax>274</xmax><ymax>109</ymax></bndbox></object><object><name>5</name><bndbox><xmin>270</xmin><ymin>26</ymin><xmax>302</xmax><ymax>97</ymax></bndbox></object><folder /></annotation>