<annotation><filename>for_xml_132485.jpg</filename><object><name>8</name><bndbox><xmin>17</xmin><ymin>5</ymin><xmax>35</xmax><ymax>37</ymax></bndbox></object><object><name>1</name><bndbox><xmin>37</xmin><ymin>5</ymin><xmax>52</xmax><ymax>37</ymax></bndbox></object><object><name>ج</name><bndbox><xmin>55</xmin><ymin>4</ymin><xmax>82</xmax><ymax>38</ymax></bndbox></object><object><name>1</name><bndbox><xmin>86</xmin><ymin>5</ymin><xmax>102</xmax><ymax>37</ymax></bndbox></object><object><name>6</name><bndbox><xmin>101</xmin><ymin>4</ymin><xmax>119</xmax><ymax>38</ymax></bndbox></object><object><name>2</name><bndbox><xmin>119</xmin><ymin>4</ymin><xmax>137</xmax><ymax>37</ymax></bndbox></object><object><name>2</name><bndbox><xmin>139</xmin><ymin>9</ymin><xmax>157</xmax><ymax>38</ymax></bndbox></object><object><name>0</name><bndbox><xmin>157</xmin><ymin>14</ymin><xmax>171</xmax><ymax>33</ymax></bndbox></object><folder /></annotation>