<annotation><filename>for_xml_123014.jpg</filename><object><name>3</name><bndbox><xmin>33</xmin><ymin>9</ymin><xmax>62</xmax><ymax>59</ymax></bndbox></object><object><name>4</name><bndbox><xmin>62</xmin><ymin>9</ymin><xmax>91</xmax><ymax>59</ymax></bndbox></object><object><name>пе</name><bndbox><xmin>92</xmin><ymin>11</ymin><xmax>145</xmax><ymax>58</ymax></bndbox></object><object><name>1</name><bndbox><xmin>148</xmin><ymin>7</ymin><xmax>173</xmax><ymax>58</ymax></bndbox></object><object><name>2</name><bndbox><xmin>174</xmin><ymin>7</ymin><xmax>204</xmax><ymax>58</ymax></bndbox></object><object><name>2</name><bndbox><xmin>204</xmin><ymin>7</ymin><xmax>232</xmax><ymax>57</ymax></bndbox></object><object><name>6</name><bndbox><xmin>238</xmin><ymin>16</ymin><xmax>266</xmax><ymax>58</ymax></bndbox></object><object><name>6</name><bndbox><xmin>266</xmin><ymin>17</ymin><xmax>294</xmax><ymax>59</ymax></bndbox></object><folder /></annotation>