<annotation><filename>for_xml_124521.jpg</filename><object><name>9</name><bndbox><xmin>42</xmin><ymin>20</ymin><xmax>82</xmax><ymax>114</ymax></bndbox></object><object><name>1</name><bndbox><xmin>87</xmin><ymin>26</ymin><xmax>116</xmax><ymax>118</ymax></bndbox></object><object><name>пе</name><bndbox><xmin>122</xmin><ymin>48</ymin><xmax>193</xmax><ymax>123</ymax></bndbox></object><object><name>7</name><bndbox><xmin>197</xmin><ymin>40</ymin><xmax>238</xmax><ymax>132</ymax></bndbox></object><object><name>5</name><bndbox><xmin>239</xmin><ymin>47</ymin><xmax>281</xmax><ymax>139</ymax></bndbox></object><object><name>1</name><bndbox><xmin>288</xmin><ymin>49</ymin><xmax>320</xmax><ymax>146</ymax></bndbox></object><object><name>1</name><bndbox><xmin>338</xmin><ymin>72</ymin><xmax>375</xmax><ymax>158</ymax></bndbox></object><object><name>0</name><bndbox><xmin>379</xmin><ymin>94</ymin><xmax>418</xmax><ymax>152</ymax></bndbox></object><folder /></annotation>