<annotation><filename>for_xml_131801.jpg</filename><object><name>4</name><bndbox><xmin>8</xmin><ymin>10</ymin><xmax>17</xmax><ymax>28</ymax></bndbox></object><object><name>3</name><bndbox><xmin>17</xmin><ymin>9</ymin><xmax>26</xmax><ymax>27</ymax></bndbox></object><object><name>пе</name><bndbox><xmin>25</xmin><ymin>9</ymin><xmax>40</xmax><ymax>25</ymax></bndbox></object><object><name>7</name><bndbox><xmin>39</xmin><ymin>7</ymin><xmax>48</xmax><ymax>23</ymax></bndbox></object><object><name>5</name><bndbox><xmin>47</xmin><ymin>6</ymin><xmax>56</xmax><ymax>22</ymax></bndbox></object><object><name>1</name><bndbox><xmin>56</xmin><ymin>5</ymin><xmax>63</xmax><ymax>21</ymax></bndbox></object><object><name>7</name><bndbox><xmin>63</xmin><ymin>5</ymin><xmax>71</xmax><ymax>20</ymax></bndbox></object><object><name>4</name><bndbox><xmin>71</xmin><ymin>4</ymin><xmax>78</xmax><ymax>18</ymax></bndbox></object><folder /></annotation>