<annotation><filename>for_xml_119478.jpg</filename><object><name>6</name><bndbox><xmin>24</xmin><ymin>2</ymin><xmax>38</xmax><ymax>23</ymax></bndbox></object><object><name>م</name><bndbox><xmin>41</xmin><ymin>3</ymin><xmax>57</xmax><ymax>25</ymax></bndbox></object><object><name>7</name><bndbox><xmin>60</xmin><ymin>5</ymin><xmax>74</xmax><ymax>28</ymax></bndbox></object><object><name>9</name><bndbox><xmin>73</xmin><ymin>7</ymin><xmax>84</xmax><ymax>29</ymax></bndbox></object><object><name>5</name><bndbox><xmin>83</xmin><ymin>9</ymin><xmax>96</xmax><ymax>30</ymax></bndbox></object><object><name>5</name><bndbox><xmin>98</xmin><ymin>15</ymin><xmax>110</xmax><ymax>33</ymax></bndbox></object><object><name>5</name><bndbox><xmin>110</xmin><ymin>16</ymin><xmax>122</xmax><ymax>34</ymax></bndbox></object><folder /></annotation>