<annotation><filename>for_xml_120956.jpg</filename><object><name>3</name><bndbox><xmin>4</xmin><ymin>5</ymin><xmax>10</xmax><ymax>14</ymax></bndbox></object><object><name>7</name><bndbox><xmin>9</xmin><ymin>5</ymin><xmax>15</xmax><ymax>14</ymax></bndbox></object><object><name>ق</name><bndbox><xmin>15</xmin><ymin>4</ymin><xmax>21</xmax><ymax>14</ymax></bndbox></object><object><name>2</name><bndbox><xmin>21</xmin><ymin>3</ymin><xmax>27</xmax><ymax>13</ymax></bndbox></object><object><name>1</name><bndbox><xmin>26</xmin><ymin>3</ymin><xmax>31</xmax><ymax>12</ymax></bndbox></object><object><name>7</name><bndbox><xmin>30</xmin><ymin>2</ymin><xmax>36</xmax><ymax>12</ymax></bndbox></object><object><name>3</name><bndbox><xmin>36</xmin><ymin>3</ymin><xmax>41</xmax><ymax>12</ymax></bndbox></object><object><name>9</name><bndbox><xmin>40</xmin><ymin>3</ymin><xmax>45</xmax><ymax>11</ymax></bndbox></object><folder /></annotation>