<annotation><filename>for_xml_125821.jpg</filename><object><name>2</name><bndbox><xmin>9</xmin><ymin>3</ymin><xmax>17</xmax><ymax>19</ymax></bndbox></object><object><name>7</name><bndbox><xmin>17</xmin><ymin>4</ymin><xmax>26</xmax><ymax>19</ymax></bndbox></object><object><name>ق</name><bndbox><xmin>27</xmin><ymin>3</ymin><xmax>39</xmax><ymax>19</ymax></bndbox></object><object><name>4</name><bndbox><xmin>41</xmin><ymin>2</ymin><xmax>50</xmax><ymax>20</ymax></bndbox></object><object><name>2</name><bndbox><xmin>49</xmin><ymin>2</ymin><xmax>58</xmax><ymax>19</ymax></bndbox></object><object><name>8</name><bndbox><xmin>57</xmin><ymin>2</ymin><xmax>66</xmax><ymax>19</ymax></bndbox></object><object><name>4</name><bndbox><xmin>67</xmin><ymin>4</ymin><xmax>75</xmax><ymax>19</ymax></bndbox></object><object><name>3</name><bndbox><xmin>75</xmin><ymin>4</ymin><xmax>84</xmax><ymax>19</ymax></bndbox></object><folder /></annotation>