<annotation><filename>for_xml_127520.jpg</filename><object><name>2</name><bndbox><xmin>21</xmin><ymin>12</ymin><xmax>41</xmax><ymax>55</ymax></bndbox></object><object><name>4</name><bndbox><xmin>40</xmin><ymin>17</ymin><xmax>61</xmax><ymax>61</ymax></bndbox></object><object><name>ق</name><bndbox><xmin>64</xmin><ymin>25</ymin><xmax>95</xmax><ymax>67</ymax></bndbox></object><object><name>7</name><bndbox><xmin>98</xmin><ymin>30</ymin><xmax>120</xmax><ymax>75</ymax></bndbox></object><object><name>1</name><bndbox><xmin>123</xmin><ymin>37</ymin><xmax>142</xmax><ymax>81</ymax></bndbox></object><object><name>7</name><bndbox><xmin>142</xmin><ymin>40</ymin><xmax>165</xmax><ymax>85</ymax></bndbox></object><object><name>1</name><bndbox><xmin>173</xmin><ymin>52</ymin><xmax>194</xmax><ymax>91</ymax></bndbox></object><object><name>1</name><bndbox><xmin>196</xmin><ymin>55</ymin><xmax>217</xmax><ymax>95</ymax></bndbox></object><folder /></annotation>