<annotation><filename>for_xml_120367.jpg</filename><object><name>3</name><bndbox><xmin>34</xmin><ymin>4</ymin><xmax>60</xmax><ymax>53</ymax></bndbox></object><object><name>7</name><bndbox><xmin>60</xmin><ymin>5</ymin><xmax>86</xmax><ymax>54</ymax></bndbox></object><object><name>ุต</name><bndbox><xmin>86</xmin><ymin>9</ymin><xmax>133</xmax><ymax>54</ymax></bndbox></object><object><name>7</name><bndbox><xmin>135</xmin><ymin>5</ymin><xmax>161</xmax><ymax>54</ymax></bndbox></object><object><name>8</name><bndbox><xmin>159</xmin><ymin>6</ymin><xmax>185</xmax><ymax>55</ymax></bndbox></object><object><name>8</name><bndbox><xmin>186</xmin><ymin>6</ymin><xmax>213</xmax><ymax>55</ymax></bndbox></object><object><name>8</name><bndbox><xmin>217</xmin><ymin>16</ymin><xmax>243</xmax><ymax>57</ymax></bndbox></object><object><name>8</name><bndbox><xmin>243</xmin><ymin>16</ymin><xmax>271</xmax><ymax>58</ymax></bndbox></object><folder /></annotation>