<annotation><filename>for_xml_133637.jpg</filename><object><name>5</name><bndbox><xmin>121</xmin><ymin>28</ymin><xmax>224</xmax><ymax>157</ymax></bndbox></object><object><name>5</name><bndbox><xmin>222</xmin><ymin>24</ymin><xmax>327</xmax><ymax>150</ymax></bndbox></object><object><name>ุต</name><bndbox><xmin>333</xmin><ymin>38</ymin><xmax>511</xmax><ymax>146</ymax></bndbox></object><object><name>8</name><bndbox><xmin>519</xmin><ymin>23</ymin><xmax>622</xmax><ymax>153</ymax></bndbox></object><object><name>4</name><bndbox><xmin>624</xmin><ymin>24</ymin><xmax>725</xmax><ymax>153</ymax></bndbox></object><object><name>4</name><bndbox><xmin>727</xmin><ymin>26</ymin><xmax>828</xmax><ymax>152</ymax></bndbox></object><object><name>3</name><bndbox><xmin>854</xmin><ymin>48</ymin><xmax>956</xmax><ymax>162</ymax></bndbox></object><object><name>4</name><bndbox><xmin>955</xmin><ymin>52</ymin><xmax>1049</xmax><ymax>162</ymax></bndbox></object><folder /></annotation>