<annotation><filename>for_xml_134510.jpg</filename><object><name>9</name><bndbox><xmin>13</xmin><ymin>5</ymin><xmax>28</xmax><ymax>31</ymax></bndbox></object><object><name>2</name><bndbox><xmin>26</xmin><ymin>4</ymin><xmax>40</xmax><ymax>31</ymax></bndbox></object><object><name>ุต</name><bndbox><xmin>40</xmin><ymin>4</ymin><xmax>62</xmax><ymax>30</ymax></bndbox></object><object><name>2</name><bndbox><xmin>62</xmin><ymin>5</ymin><xmax>77</xmax><ymax>31</ymax></bndbox></object><object><name>4</name><bndbox><xmin>76</xmin><ymin>5</ymin><xmax>90</xmax><ymax>31</ymax></bndbox></object><object><name>7</name><bndbox><xmin>89</xmin><ymin>6</ymin><xmax>104</xmax><ymax>31</ymax></bndbox></object><object><name>3</name><bndbox><xmin>106</xmin><ymin>10</ymin><xmax>119</xmax><ymax>32</ymax></bndbox></object><object><name>4</name><bndbox><xmin>118</xmin><ymin>9</ymin><xmax>132</xmax><ymax>32</ymax></bndbox></object><folder /></annotation>