<annotation><filename>for_xml_134931.jpg</filename><object><name>6</name><bndbox><xmin>23</xmin><ymin>3</ymin><xmax>44</xmax><ymax>34</ymax></bndbox></object><object><name>9</name><bndbox><xmin>44</xmin><ymin>4</ymin><xmax>63</xmax><ymax>36</ymax></bndbox></object><object><name>ุต</name><bndbox><xmin>65</xmin><ymin>9</ymin><xmax>99</xmax><ymax>36</ymax></bndbox></object><object><name>7</name><bndbox><xmin>99</xmin><ymin>7</ymin><xmax>120</xmax><ymax>39</ymax></bndbox></object><object><name>4</name><bndbox><xmin>121</xmin><ymin>7</ymin><xmax>141</xmax><ymax>40</ymax></bndbox></object><object><name>2</name><bndbox><xmin>141</xmin><ymin>7</ymin><xmax>161</xmax><ymax>40</ymax></bndbox></object><object><name>2</name><bndbox><xmin>164</xmin><ymin>14</ymin><xmax>184</xmax><ymax>40</ymax></bndbox></object><object><name>1</name><bndbox><xmin>184</xmin><ymin>13</ymin><xmax>202</xmax><ymax>40</ymax></bndbox></object><folder /></annotation>