<annotation><filename>for_xml_134911.jpg</filename><object><name>4</name><bndbox><xmin>41</xmin><ymin>9</ymin><xmax>72</xmax><ymax>68</ymax></bndbox></object><object><name>5</name><bndbox><xmin>72</xmin><ymin>12</ymin><xmax>108</xmax><ymax>69</ymax></bndbox></object><object><name>ุต</name><bndbox><xmin>110</xmin><ymin>19</ymin><xmax>167</xmax><ymax>68</ymax></bndbox></object><object><name>2</name><bndbox><xmin>171</xmin><ymin>16</ymin><xmax>203</xmax><ymax>75</ymax></bndbox></object><object><name>8</name><bndbox><xmin>202</xmin><ymin>18</ymin><xmax>236</xmax><ymax>77</ymax></bndbox></object><object><name>5</name><bndbox><xmin>236</xmin><ymin>20</ymin><xmax>272</xmax><ymax>81</ymax></bndbox></object><object><name>4</name><bndbox><xmin>279</xmin><ymin>32</ymin><xmax>310</xmax><ymax>83</ymax></bndbox></object><object><name>4</name><bndbox><xmin>310</xmin><ymin>34</ymin><xmax>342</xmax><ymax>86</ymax></bndbox></object><folder /></annotation>