<annotation><filename>for_xml_1274.jpg</filename><object><name>7</name><bndbox><xmin>42</xmin><ymin>33</ymin><xmax>78</xmax><ymax>107</ymax></bndbox></object><object><name>5</name><bndbox><xmin>74</xmin><ymin>33</ymin><xmax>109</xmax><ymax>106</ymax></bndbox></object><object><name>د</name><bndbox><xmin>110</xmin><ymin>48</ymin><xmax>159</xmax><ymax>107</ymax></bndbox></object><object><name>8</name><bndbox><xmin>158</xmin><ymin>48</ymin><xmax>193</xmax><ymax>111</ymax></bndbox></object><object><name>9</name><bndbox><xmin>188</xmin><ymin>51</ymin><xmax>222</xmax><ymax>121</ymax></bndbox></object><object><name>6</name><bndbox><xmin>215</xmin><ymin>52</ymin><xmax>252</xmax><ymax>123</ymax></bndbox></object><object><name>1</name><bndbox><xmin>248</xmin><ymin>65</ymin><xmax>287</xmax><ymax>129</ymax></bndbox></object><object><name>1</name><bndbox><xmin>284</xmin><ymin>75</ymin><xmax>317</xmax><ymax>129</ymax></bndbox></object><folder /></annotation>