<annotation><filename>for_xml_4338.jpg</filename><object><name>5</name><bndbox><xmin>64</xmin><ymin>28</ymin><xmax>120</xmax><ymax>121</ymax></bndbox></object><object><name>3</name><bndbox><xmin>125</xmin><ymin>24</ymin><xmax>179</xmax><ymax>115</ymax></bndbox></object><object><name>د</name><bndbox><xmin>192</xmin><ymin>21</ymin><xmax>268</xmax><ymax>112</ymax></bndbox></object><object><name>5</name><bndbox><xmin>273</xmin><ymin>16</ymin><xmax>329</xmax><ymax>124</ymax></bndbox></object><object><name>4</name><bndbox><xmin>334</xmin><ymin>15</ymin><xmax>379</xmax><ymax>112</ymax></bndbox></object><object><name>7</name><bndbox><xmin>380</xmin><ymin>18</ymin><xmax>425</xmax><ymax>112</ymax></bndbox></object><object><name>1</name><bndbox><xmin>452</xmin><ymin>42</ymin><xmax>494</xmax><ymax>115</ymax></bndbox></object><object><name>0</name><bndbox><xmin>506</xmin><ymin>49</ymin><xmax>544</xmax><ymax>113</ymax></bndbox></object><folder /></annotation>